MsCoppel/Base.py
MsCoppel/ColorJson.py
MsCoppel/ErrorMs.py
MsCoppel/Fork.py
MsCoppel/ForkHttp.py
MsCoppel/HttpErrors.py
MsCoppel/HttpResponse.py
MsCoppel/HttpTransit.py
MsCoppel/LogssBottle.py
MsCoppel/MsManager.py
MsCoppel/NatsBase.py
MsCoppel/Util.py
MsCoppel/Worker.py
MsCoppel/__init__.py
MsCoppel/http_server.py
MsCoppel/loggs.py
MsCoppel/loggsWrapper.py
MsCoppel/microservices.py
MsCoppel/ms_base.py
MsCoppel/options.py
MsCoppel/types.py
MsCoppel/version_framework.py
tests/__init__.py
tests/test_error.py
MsCoppel-1.7.0.dist-info/LICENSE.txt
MsCoppel-1.7.0.dist-info/METADATA
MsCoppel-1.7.0.dist-info/WHEEL
MsCoppel-1.7.0.dist-info/top_level.txt
MsCoppel-1.7.0.dist-info/RECORD
