Metadata-Version: 2.1
Name: MsCoppel
Version: 1.7.0
Summary: Libreria para microservicios basados en mensajes
Home-page: UNKNOWN
Author: Enoi Barrera Guzman
Author-email: zafiro3000x@gmail.com
License: UNKNOWN
Platform: UNKNOWN
Classifier: Programming Language :: Python :: 3
Requires-Dist: kafka-python (==2.0.1)
Requires-Dist: Logbook
Requires-Dist: asyncio-nats-client (==0.10.0)
Requires-Dist: jaeger-client (==4.3.0)
Requires-Dist: fluent-logger (==0.9.6)
Requires-Dist: bottle (==0.12.18)
Requires-Dist: coloredlogs (==14.0)
Requires-Dist: colorama (==0.4.3)
Requires-Dist: Pygments (==2.6.1)
Requires-Dist: waitress (==1.4.4)
Requires-Dist: redis (==3.5.3)
Requires-Dist: contextvars (==2.4)
Requires-Dist: requests (==2.20.0)
Requires-Dist: autodynatrace (==1.0.75)
